LICENCE
MANIFEST.in
README.md
setup.py
allianceauth_site_claim.egg-info/PKG-INFO
allianceauth_site_claim.egg-info/SOURCES.txt
allianceauth_site_claim.egg-info/dependency_links.txt
allianceauth_site_claim.egg-info/requires.txt
allianceauth_site_claim.egg-info/top_level.txt
siteclaim/__init__.py
siteclaim/admin.py
siteclaim/app_settings.py
siteclaim/apps.py
siteclaim/auth_hooks.py
siteclaim/models.py
siteclaim/providers.py
siteclaim/tasks.py
siteclaim/__pycache__/__init__.cpython-39.pyc
siteclaim/cogs/ess.py
siteclaim/cogs/sites.py
siteclaim/management/commands/__init.py
siteclaim/management/commands/sc_setup_sde.py
siteclaim/migrations/0001_initial.py
siteclaim/migrations/0002_rename_catconfiguration_siteclaimconfiguration.py
siteclaim/migrations/0003_siteclaimconfiguration_valid_site_regions.py
siteclaim/migrations/0004_site.py
siteclaim/migrations/0005_siteclaimconfiguration_site_claim_output_channel.py
siteclaim/migrations/0006_siteclaimconfiguration_ess_output_channel_and_more.py
siteclaim/migrations/__init__.py